yggdrasil_address/__init__.py
yggdrasil_address-0.0.1.post3.dist-info/LICENSE
yggdrasil_address-0.0.1.post3.dist-info/METADATA
yggdrasil_address-0.0.1.post3.dist-info/WHEEL
yggdrasil_address-0.0.1.post3.dist-info/top_level.txt
yggdrasil_address-0.0.1.post3.dist-info/RECORD
