Metadata-Version: 2.1
Name: yggdrasil_address
Version: 0.0.1.post3
Summary: Small tool for converting yggdrasil addresses
Home-page: https://git.cofob.ru/cofob/yggdrasil-address
Author: cofob
Author-email: c@cofob.ru
License: UNKNOWN
Platform: UNKNOWN
Classifier: Programming Language :: Python :: 3
Classifier: License :: OSI Approved :: GNU General Public License v3 (GPLv3)
Classifier: Operating System :: OS Independent
Requires-Python: >=3.6
License-File: LICENSE
